{
  "converged": true,
  "iterations": 1,
  "loss_before": 3.944304526105059e-32,
  "loss_after": 3.944304526105059e-32,
  "cpi_error_percent": 0.0,
  "corrections": {
    "cor.oscillator": 0.1,
    "cor.envelope": 0.1,
    "cor.register": 0.1,
    "cor.memory": 0.1,
    "cor.control": 0.1,
    "cor.mixing": 0.1
  },
  "free_parameters": [
    "cor.control",
    "cor.envelope",
    "cor.memory",
    "cor.mixing",
    "cor.oscillator",
    "cor.register"
  ],
  "residuals_before": {
    "typical": 0.0,
    "compute": 4.440892098500626e-16,
    "memory": 0.0,
    "control": 0.0,
    "mixed": 0.0
  },
  "residuals_after": {
    "typical": 0.0,
    "compute": 4.440892098500626e-16,
    "memory": 0.0,
    "control": 0.0,
    "mixed": 0.0
  }
}
