{
  "processor": "TI SBP0401",
  "manufacturer": "Texas Instruments",
  "year": 1976,
  "schema_version": "1.0",
  "source": "SBP0401 datasheet",
  "base_architecture": "SBP0400",
  "base_timing_reference": "sbp0400",
  "timing_notes": "SBP0400 variant with expanded I/O. Same instruction timing.",
  "instruction_count": 16,
  "instructions": [
    {
      "mnemonic": "ADD",
      "opcode": "0x0",
      "bytes": 1,
      "cycles": 4,
      "category": "alu",
      "addressing_mode": "register",
      "flags_affected": "C",
      "notes": "Add"
    },
    {
      "mnemonic": "SUB",
      "opcode": "0x1",
      "bytes": 1,
      "cycles": 4,
      "category": "alu",
      "addressing_mode": "register",
      "flags_affected": "C",
      "notes": "Subtract"
    },
    {
      "mnemonic": "AND",
      "opcode": "0x2",
      "bytes": 1,
      "cycles": 4,
      "category": "alu",
      "addressing_mode": "register",
      "flags_affected": "Z",
      "notes": "AND"
    },
    {
      "mnemonic": "MOV",
      "opcode": "0x7",
      "bytes": 1,
      "cycles": 4,
      "category": "data_transfer",
      "addressing_mode": "register",
      "flags_affected": "",
      "notes": "Move"
    },
    {
      "mnemonic": "LDI",
      "opcode": "0x8",
      "bytes": 2,
      "cycles": 6,
      "category": "data_transfer",
      "addressing_mode": "immediate",
      "flags_affected": "",
      "notes": "Load imm"
    },
    {
      "mnemonic": "IN",
      "opcode": "0x9",
      "bytes": 1,
      "cycles": 6,
      "category": "io",
      "addressing_mode": "port",
      "flags_affected": "",
      "notes": "Input"
    },
    {
      "mnemonic": "OUT",
      "opcode": "0xA",
      "bytes": 1,
      "cycles": 6,
      "category": "io",
      "addressing_mode": "port",
      "flags_affected": "",
      "notes": "Output"
    },
    {
      "mnemonic": "JMP",
      "opcode": "0xB",
      "bytes": 2,
      "cycles": 6,
      "category": "control",
      "addressing_mode": "absolute",
      "flags_affected": "",
      "notes": "Jump"
    },
    {
      "mnemonic": "NOP",
      "opcode": "0xF",
      "bytes": 1,
      "cycles": 4,
      "category": "nop",
      "addressing_mode": "implied",
      "flags_affected": "",
      "notes": ""
    }
  ]
}
