{
  "processor": "hypersparc",
  "date": "2026-01-31",
  "method": "ridge",
  "converged": true,
  "iterations": 9,
  "loss_before": 0.006255,
  "loss_after": 0.0,
  "cpi_error_percent": 0.0,
  "message": "`gtol` termination condition is satisfied.",
  "corrections": {
    "cor.alu": -0.74271,
    "cor.branch": 1.083203,
    "cor.divide": -13.96362,
    "cor.load": -3.225545,
    "cor.multiply": 0.596151,
    "cor.store": -1.240396
  },
  "residuals_before": {
    "typical": -0.0788,
    "compute": -0.0493,
    "memory": -0.1183,
    "control": -0.0493,
    "mixed": -0.0788
  },
  "residuals_after": {
    "typical": 0.0001,
    "compute": -0.0001,
    "memory": -0.0001,
    "control": -0.0001,
    "mixed": 0.0002
  },
  "free_parameters": [
    "cache.l1_hit_rate",
    "cache.l2_hit_rate",
    "cor.alu",
    "cor.branch",
    "cor.divide",
    "cor.load",
    "cor.multiply",
    "cor.store"
  ]
}