{
  "processor": "upd7759",
  "date": "2026-01-30",
  "converged": true,
  "iterations": 37,
  "loss_before": 0.0045,
  "loss_after": 0.0,
  "cpi_error_percent": 0.0,
  "message": "`gtol` termination condition is satisfied.",
  "corrections": {
    "cor.oscillator": -0.276935,
    "cor.envelope": 0.723065,
    "cor.register": 0.799947,
    "cor.memory": 0.723065,
    "cor.control": 0.646182,
    "cor.mixing": 2.5693
  },
  "residuals_before": {
    "typical": 0.0,
    "compute": 0.1,
    "memory": -0.1,
    "control": 0.0,
    "mixed": -0.05
  },
  "residuals_after": {
    "typical": -0.0,
    "compute": 0.0,
    "memory": -0.0,
    "control": 0.0,
    "mixed": 0.0
  },
  "free_parameters": [
    "cor.control",
    "cor.envelope",
    "cor.memory",
    "cor.mixing",
    "cor.oscillator",
    "cor.register"
  ]
}