{
  "processor": "microsparc_ii",
  "date": "2026-01-31",
  "converged": false,
  "iterations": 200,
  "loss_before": 0.001604,
  "loss_after": 0.0,
  "cpi_error_percent": 0.0,
  "message": "The maximum number of function evaluations is exceeded.",
  "corrections": {
    "cor.alu": 0.7623926379851399,
    "cor.branch": -0.798083286845334,
    "cor.divide": -9.995703662692987,
    "cor.load": -3.9202458787519827,
    "cor.multiply": -5.6004629109976864,
    "cor.store": 0.8437994823070268
  },
  "cache_parameters": {
    "cache.l1_hit_rate": 0.925125,
    "cache.l1_latency": 1.0,
    "cache.dram_latency": 11.0,
    "cache.l2_hit_rate": 0.998934,
    "cache.l2_latency": 16.5
  },
  "residuals_before": {
    "typical": -0.0641,
    "compute": 0.0104,
    "memory": -0.0025,
    "control": -0.0019,
    "mixed": 0.0616
  },
  "residuals_after": {
    "typical": 0.0,
    "compute": 0.0,
    "memory": -0.0,
    "control": 0.0,
    "mixed": -0.0
  },
  "free_parameters": [
    "cache.l1_hit_rate",
    "cache.l2_hit_rate",
    "cor.alu",
    "cor.branch",
    "cor.divide",
    "cor.load",
    "cor.multiply",
    "cor.store"
  ]
}
